ulid2.py
ulid2-0.3.0.dist-info/LICENSE
ulid2-0.3.0.dist-info/METADATA
ulid2-0.3.0.dist-info/WHEEL
ulid2-0.3.0.dist-info/top_level.txt
ulid2-0.3.0.dist-info/RECORD
