Metadata-Version: 1.0
Name: ulid2
Version: 0.3.0
Summary: ULID encoding/decoding for Python
Home-page: https://github.com/valohai/ulid2
Author: Aarni Koskela
Author-email: akx@iki.fi
License: MIT
Platform: UNKNOWN
